{
  "type": "minecraft:chest",
  "pools": [
    {
      "rolls": {
        "min": 5.0,
        "max": 7.0,
        "type": "minecraft:uniform"
      },
      "entries": [
        {
          "name": "minecraft:ghast_tear",
          "type": "minecraft:item"
        },
        {
          "name": "minecraft:wither_rose",
          "type": "minecraft:item"
        },
        {
          "name": "minecraft:warped_fungus",
          "type": "minecraft:item"
        },
        {
          "name": "minecraft:crimson_fungus",
          "type": "minecraft:item"
        },
        {
          "name": "minecraft:magma_cream",
          "type": "minecraft:item"
        },
        {
          "functions": [
            {
              "levels": {
                "min": 25.0,
                "max": 35.0,
                "type": "minecraft:uniform"
              },
              "options": "#minecraft:on_random_loot",
              "function": "minecraft:enchant_with_levels"
            }
          ],
          "name": "minecraft:golden_sword",
          "type": "minecraft:item"
        },
        {
          "functions": [
            {
              "count": {
                "min": 1.0,
                "max": 2.0,
                "type": "minecraft:uniform"
              },
              "add": false,
              "function": "minecraft:set_count"
            }
          ],
          "name": "minecraft:nether_wart",
          "type": "minecraft:item"
        },
        {
          "functions": [
            {
              "count": {
                "min": 1.0,
                "max": 2.0,
                "type": "minecraft:uniform"
              },
              "add": false,
              "function": "minecraft:set_count"
            }
          ],
          "name": "minecraft:blaze_powder",
          "type": "minecraft:item"
        },
        {
          "name": "minecraft:golden_apple",
          "type": "minecraft:item"
        },
        {
          "name": "minecraft:saddle",
          "type": "minecraft:item"
        },
        {
          "name": "minecraft:warped_fungus_on_a_stick",
          "type": "minecraft:item"
        }
      ]
    }
  ]
}